{
  "hourly-sum-purchases-for-stores": {
    "display_name": "Sum Purchases for Stores (Hourly)!",
    "query": {
      "analysis_type": "sum",
      "event_collection": "purchases",
      "target_property": "price",
      "timeframe": "this_500_hours",
      "interval": "hourly",
      "timezone": "UTC"
    },
    "index_by": ["store.id"]
  },
  "daily-sum-purchases-for-stores": {
    "display_name": "Sum Purchases for Stores (Daily)!",
    "query": {
      "analysis_type": "sum",
      "event_collection": "purchases",
      "target_property": "price",
      "timeframe": "this_500_days",
      "interval": "daily",
      "timezone": "UTC"
    },
    "index_by": ["store.id"]
  }
}
